polymarket_provider-0.1.1.dist-info/METADATA
polymarket_provider-0.1.1.dist-info/WHEEL
polymarket_provider/__init__.py
polymarket_provider/polymarket_provider.abi3.so
polymarket_provider-0.1.1.dist-info/RECORD
