Metadata-Version: 2.4
Name: polymarket-provider
Version: 0.1.1
Classifier: Development Status :: 4 - Beta
Classifier: Intended Audience :: Developers
Classifier: License :: OSI Approved :: MIT License
Classifier: Programming Language :: Python :: 3
Classifier: Programming Language :: Python :: 3.11
Classifier: Programming Language :: Python :: 3.12
Classifier: Programming Language :: Python :: 3.13
Classifier: Programming Language :: Rust
Classifier: Topic :: Database
Summary: Polymarket data provider for Python - Query Polymarket data from local DuckDB
Keywords: polymarket,duckdb,prediction-market
Author: cupnfish
License: MIT
Requires-Python: >=3.11
Project-URL: Homepage, https://github.com/cupnfish/polymarket-hyperindex
Project-URL: Repository, https://github.com/cupnfish/polymarket-hyperindex
